formfill/__init__.py
formfill/cli.py
formfill/fill.py
formfill/image_utils.py
formfill/modified_loop.py
formfill/pdf_editor.py
formfill/anthropic_computer_use_demo/__init__.py
formfill/anthropic_computer_use_demo/loop.py
formfill/anthropic_computer_use_demo/tools/__init__.py
formfill/anthropic_computer_use_demo/tools/base.py
formfill/anthropic_computer_use_demo/tools/collection.py
formfill/anthropic_computer_use_demo/tools/computer.py
formfill/anthropic_computer_use_demo/tools/run.py
formfill-0.1.0.dist-info/METADATA
formfill-0.1.0.dist-info/WHEEL
formfill-0.1.0.dist-info/entry_points.txt
formfill-0.1.0.dist-info/top_level.txt
formfill-0.1.0.dist-info/RECORD
