Metadata-Version: 2.1
Name: formfill
Version: 0.1.0
Summary: A CLI tool for automatically filling PDF forms using Claude
Home-page: 
Author: William Horton
License: MIT
Keywords: pdf form fill automation claude anthropic
Classifier: Development Status :: 3 - Alpha
Classifier: Intended Audience :: End Users/Desktop
Classifier: License :: OSI Approved :: MIT License
Classifier: Programming Language :: Python :: 3
Classifier: Programming Language :: Python :: 3.8
Classifier: Programming Language :: Python :: 3.9
Classifier: Programming Language :: Python :: 3.10
Classifier: Programming Language :: Python :: 3.11
Classifier: Programming Language :: Python :: 3.12
Classifier: Programming Language :: Python :: 3.13
Requires-Python: >=3.8
Requires-Dist: anthropic
Requires-Dist: pdf2image
Requires-Dist: Pillow
